LICENSE
MANIFEST.in
README.md
requirements.txt
setup.py
dclist/__init__.py
dclist/client.py
dclist/errors.py
dclist/gqlhttp.py
dclist.py.egg-info/PKG-INFO
dclist.py.egg-info/SOURCES.txt
dclist.py.egg-info/dependency_links.txt
dclist.py.egg-info/requires.txt
dclist.py.egg-info/top_level.txt
dclist/helpers/queries.py