Metadata-Version: 2.1
Name: dclist.py
Version: 0.1.6
Summary: GQL-API wrapper for dclist.net
Home-page: https://github.com/dclist/python-sdk
Author: ilkergzlkkr
Author-email: guzelkokarilker@gmail.com
License: MIT
Download-URL: https://github.com/dclist/python-sdk.git
Platform: UNKNOWN
Classifier: License :: OSI Approved :: MIT License
Classifier: Programming Language :: Python :: 3
Classifier: Natural Language :: English
Classifier: Operating System :: OS Independent
Classifier: Topic :: Internet
Classifier: Topic :: Software Development :: Libraries
Classifier: Topic :: Software Development :: Libraries :: Python Modules
Classifier: Topic :: Utilities
Provides-Extra: dev
